exoanchor/cli.py
exoanchor/engine.py
exoanchor/pypi.py
exoanchor/sandbox.py
exoanchor-0.1.0.dist-info/licenses/LICENSE
exoanchor-0.1.0.dist-info/METADATA
exoanchor-0.1.0.dist-info/WHEEL
exoanchor-0.1.0.dist-info/entry_points.txt
exoanchor-0.1.0.dist-info/top_level.txt
exoanchor-0.1.0.dist-info/RECORD
