Metadata-Version: 2.4
Name: exoanchor
Version: 0.1.0
Summary: A CLI tool to test if your Python project will break before you upgrade dependencies.
Author-email: Jonathan R Belanger <jonathan.r.belanger@gmail.com>
License: MIT
Requires-Python: >=3.8
License-File: LICENSE
Requires-Dist: click
Requires-Dist: requests
Requires-Dist: packaging
Dynamic: license-file
